karawun/__init__.py
karawun/_version.py
karawun/ciedicom.py
karawun/commandline.py
karawun/karawun.py
karawun-0.2.5.4.dist-info/LICENSE
karawun-0.2.5.4.dist-info/METADATA
karawun-0.2.5.4.dist-info/WHEEL
karawun-0.2.5.4.dist-info/entry_points.txt
karawun-0.2.5.4.dist-info/top_level.txt
karawun-0.2.5.4.dist-info/RECORD
