Metadata-Version: 2.1
Name: karawun
Version: 0.2.5.4
Summary: DICOM image, segmgmentation image and fibre object converter
Home-page: https://developmentalimagingmcri.github.io/karawun/
Author: Richard Beare
Author-email: richard.beare@mcri.edu.au
License: Apache License, Version 2.0
Platform: UNKNOWN
Classifier: Programming Language :: Python :: 3
Classifier: License :: OSI Approved :: Apache Software License
Classifier: Operating System :: OS Independent
Classifier: Development Status :: 5 - Production/Stable
Classifier: Environment :: Console
Classifier: Intended Audience :: Healthcare Industry
Classifier: Intended Audience :: Science/Research
Classifier: Natural Language :: English
Classifier: Topic :: Scientific/Engineering :: Medical Science Apps.
Requires-Python: >=3.6
Requires-Dist: numpy (>=1.13.0)
Requires-Dist: pydicom (==1.4.2)
Requires-Dist: SimpleITK (<=2.0.2,>=1.2.0)
